proteca/__init__.py
proteca/attacks.py
proteca/defences.py
proteca/synset_words.txt
PROTECA-0.1.4.dist-info/LICENSE
PROTECA-0.1.4.dist-info/METADATA
PROTECA-0.1.4.dist-info/WHEEL
PROTECA-0.1.4.dist-info/top_level.txt
PROTECA-0.1.4.dist-info/RECORD
